{
  "version": "7",
  "dialect": "postgresql",
  "entries": [
    {
      "idx": 0,
      "version": "7",
      "when": 1719249740014,
      "tag": "0000_white_donald_blake",
      "breakpoints": true
    },
    {
      "idx": 1,
      "version": "7",
      "when": 1719278860367,
      "tag": "0001_legal_sir_ram",
      "breakpoints": true
    },
    {
      "idx": 2,
      "version": "7",
      "when": 1719281045299,
      "tag": "0002_regular_the_captain",
      "breakpoints": true
    },
    {
      "idx": 3,
      "version": "7",
      "when": 1719281335858,
      "tag": "0003_powerful_johnny_storm",
      "breakpoints": true
    },
    {
      "idx": 4,
      "version": "7",
      "when": 1719285320282,
      "tag": "0004_workable_black_tarantula",
      "breakpoints": true
    }
  ]
}